geomdl/shapes/__init__.py
geomdl/shapes/analytic.py
geomdl/shapes/curve2d.py
geomdl/shapes/surface.py
geomdl/shapes/volume.py
geomdl.shapes-1.3.0.dist-info/LICENSE
geomdl.shapes-1.3.0.dist-info/METADATA
geomdl.shapes-1.3.0.dist-info/WHEEL
geomdl.shapes-1.3.0.dist-info/top_level.txt
geomdl.shapes-1.3.0.dist-info/RECORD
