Metadata-Version: 2.1
Name: geomdl.shapes
Version: 1.3.0
Summary: Generate common B-spline, NURBS and analytic geometries
Home-page: https://github.com/orbingol/geomdl-shapes
Author: Onur Rauf Bingol
Author-email: nurbs-python@googlegroups.com
License: MIT
Project-URL: Documentation, http://geomdl-shapes.readthedocs.io/
Project-URL: Source, https://github.com/orbingol/geomdl-shapes
Project-URL: Tracker, https://github.com/orbingol/geomdl-shapes/issues
Keywords: NURBS B-Spline curve surface volume CAD modeling visualization
Platform: UNKNOWN
Classifier: Development Status :: 5 - Production/Stable
Classifier: Intended Audience :: Science/Research
Classifier: License :: OSI Approved :: MIT License
Classifier: Topic :: Scientific/Engineering :: Mathematics
Classifier: Topic :: Scientific/Engineering :: Visualization
Classifier: Operating System :: OS Independent
Classifier: Programming Language :: Python :: 2
Classifier: Programming Language :: Python :: 2.7
Classifier: Programming Language :: Python :: 3
Classifier: Programming Language :: Python :: 3.4
Classifier: Programming Language :: Python :: 3.5
Classifier: Programming Language :: Python :: 3.6
Classifier: Programming Language :: Python :: 3.7
Requires-Dist: geomdl (>=5.2.0)
